{
  "data": [
    {
      "title": "Business on the Books",
      "subData": [
        {
          "title": "Room Nights",
          "data": [
            { "num": 173 },
            { "num": 380 },
            { "num": 289 },
            { "num": 225 },
            { "num": 398 },
            { "num": 351 },
            { "num": 309 },
            { "num": 311 },
            { "num": 263 },
            { "num": 302 },
            { "num": 364 },
            { "num": 357 },
            { "num": 274 },
            { "num": 277 },
            { "num": 350 },
            { "num": 172 },
            { "num": 171 },
            { "num": 272 },
            { "num": 356 },
            { "num": 360 },
            { "num": 183 },
            { "num": 240 },
            { "num": 335 },
            { "num": 214 },
            { "num": 341 },
            { "num": 202 },
            { "num": 304 },
            { "num": 170 },
            { "num": 204 },
            { "num": 248 },
            { "num": 0 }
          ],
          "total": 8395
        },
        {
          "title": "OCC",
          "data": [
            { "num": 55 },
            { "num": 53 },
            { "num": 70 },
            { "num": 70 },
            { "num": 50 },
            { "num": 44 },
            { "num": 48 },
            { "num": 59 },
            { "num": 76 },
            { "num": 46 },
            { "num": 79 },
            { "num": 77 },
            { "num": 54 },
            { "num": 41 },
            { "num": 81 },
            { "num": 52 },
            { "num": 45 },
            { "num": 86 },
            { "num": 74 },
            { "num": 67 },
            { "num": 75 },
            { "num": 59 },
            { "num": 62 },
            { "num": 54 },
            { "num": 78 },
            { "num": 96 },
            { "num": 63 },
            { "num": 78 },
            { "num": 66 },
            { "num": 70 },
            { "num": 0 }
          ],
          "total": 64
        },
        {
          "title": "ADR",
          "data": [
            { "num": 370 },
            { "num": 363 },
            { "num": 271 },
            { "num": 408 },
            { "num": 326 },
            { "num": 273 },
            { "num": 235 },
            { "num": 225 },
            { "num": 393 },
            { "num": 295 },
            { "num": 224 },
            { "num": 271 },
            { "num": 301 },
            { "num": 241 },
            { "num": 322 },
            { "num": 309 },
            { "num": 255 },
            { "num": 222 },
            { "num": 313 },
            { "num": 323 },
            { "num": 332 },
            { "num": 343 },
            { "num": 307 },
            { "num": 362 },
            { "num": 199 },
            { "num": 333 },
            { "num": 288 },
            { "num": 333 },
            { "num": 332 },
            { "num": 249 },
            { "num": 0 }
          ],
          "total": 300.6
        },
        {
          "title": "Revenue",
          "data": [
            { "num": 64010 },
            { "num": 137940 },
            { "num": 78319 },
            { "num": 91800 },
            { "num": 129748 },
            { "num": 95823 },
            { "num": 72615 },
            { "num": 69975 },
            { "num": 103359 },
            { "num": 89090 },
            { "num": 81536 },
            { "num": 96747 },
            { "num": 82474 },
            { "num": 66757 },
            { "num": 112700 },
            { "num": 53148 },
            { "num": 43605 },
            { "num": 60384 },
            { "num": 111428 },
            { "num": 116280 },
            { "num": 60756 },
            { "num": 82320 },
            { "num": 102845 },
            { "num": 77468 },
            { "num": 67859 },
            { "num": 67266 },
            { "num": 87552 },
            { "num": 56610 },
            { "num": 67728 },
            { "num": 61752 },
            { "num": 0 }
          ],
          "total": 2523537
        }
      ]
    },
    {
      "title": "Pick up since Yesterday",
      "subData": [
        {
          "title": "Room Nights",
          "data": [
            { "num": 34 },
            { "num": 20 },
            { "num": 23 },
            { "num": 36 },
            { "num": 43 },
            { "num": 11 },
            { "num": 47 },
            { "num": 14 },
            { "num": 40 },
            { "num": 15 },
            { "num": 28 },
            { "num": 16 },
            { "num": 40 },
            { "num": 48 },
            { "num": 15 },
            { "num": 28 },
            { "num": 10 },
            { "num": 34 },
            { "num": 36 },
            { "num": 13 },
            { "num": 26 },
            { "num": 29 },
            { "num": 42 },
            { "num": 37 },
            { "num": 25 },
            { "num": 27 },
            { "num": 37 },
            { "num": 33 },
            { "num": 33 },
            { "num": 26 },
            { "num": 0 }
          ],
          "total": 866
        },
        {
          "title": "ADR",
          "data": [
            { "num": 7 },
            { "num": 7 },
            { "num": 2 },
            { "num": -1 },
            { "num": 3 },
            { "num": 6 },
            { "num": 8 },
            { "num": -3 },
            { "num": 3 },
            { "num": 3 },
            { "num": 9 },
            { "num": 2 },
            { "num": 2 },
            { "num": 9 },
            { "num": -1.4 },
            { "num": 6 },
            { "num": 4 },
            { "num": 8 },
            { "num": 8 },
            { "num": 2 },
            { "num": 7 },
            { "num": 3 },
            { "num": 7 },
            { "num": -2.5 },
            { "num": 9 },
            { "num": 8 },
            { "num": 6 },
            { "num": -4 },
            { "num": 5 },
            { "num": 9 },
            { "num": 0 }
          ],
          "total": 4.4
        },
        {
          "title": "Revenue",
          "data": [
            { "num": 917 },
            { "num": 2855 },
            { "num": -742 },
            { "num": -667 },
            { "num": 2125 },
            { "num": 1048 },
            { "num": -1006 },
            { "num": 869 },
            { "num": -689 },
            { "num": 1512 },
            { "num": 730 },
            { "num": -555 },
            { "num": 2028 },
            { "num": 1637 },
            { "num": 1636 },
            { "num": 2515 },
            { "num": 444 },
            { "num": 1237 },
            { "num": -455 },
            { "num": 2076 },
            { "num": -1198 },
            { "num": 780 },
            { "num": -174 },
            { "num": 1901 },
            { "num": 1080 },
            { "num": 460 },
            { "num": -1148 },
            { "num": 1476 },
            { "num": 468 },
            { "num": 2178 },
            { "num": 1036 }
          ],
          "total": 3321.5
        }
      ]
    },
    {
      "title": "Availability & Rates",
      "subData": [
        {
          "title": "Available Rooms",
          "data": [
            { "num": -173 },
            { "num": -380 },
            { "num": -289 },
            { "num": -225 },
            { "num": -398 },
            { "num": -351 },
            { "num": -309 },
            { "num": -311 },
            { "num": -263 },
            { "num": -302 },
            { "num": -364 },
            { "num": -357 },
            { "num": -274 },
            { "num": -277 },
            { "num": -350 },
            { "num": -172 },
            { "num": -171 },
            { "num": -272 },
            { "num": -356 },
            { "num": -360 },
            { "num": -183 },
            { "num": -240 },
            { "num": -335 },
            { "num": -214 },
            { "num": -341 },
            { "num": -202 },
            { "num": -304 },
            { "num": -170 },
            { "num": -204 },
            { "num": -248 },
            { "num": -185 }
          ],
          "total": ""
        },
        {
          "title": "Selling Rate",
          "data": [
            { "num": 331 },
            { "num": 274 },
            { "num": 347 },
            { "num": 277 },
            { "num": 357 },
            { "num": 228 },
            { "num": 309 },
            { "num": 299 },
            { "num": 361 },
            { "num": 321 },
            { "num": 398 },
            { "num": 257 },
            { "num": 471 },
            { "num": 438 },
            { "num": 428 },
            { "num": 214 },
            { "num": 460 },
            { "num": 497 },
            { "num": 283 },
            { "num": 297 },
            { "num": 480 },
            { "num": 334 },
            { "num": 399 },
            { "num": 430 },
            { "num": 252 },
            { "num": 391 },
            { "num": 470 },
            { "num": 421 },
            { "num": 275 },
            { "num": 396 },
            { "num": 0 }
          ],
          "total": 356.5
        },
        {
          "title": "Market Rate",
          "data": [
            { "num": 175 },
            { "num": 436 },
            { "num": 261 },
            { "num": 275 },
            { "num": 518 },
            { "num": 528 },
            { "num": 379 },
            { "num": 513 },
            { "num": 432 },
            { "num": 380 },
            { "num": 247 },
            { "num": 236 },
            { "num": 490 },
            { "num": 291 },
            { "num": 194 },
            { "num": 337 },
            { "num": 483 },
            { "num": 406 },
            { "num": 374 },
            { "num": 445 },
            { "num": 577 },
            { "num": 396 },
            { "num": 560 },
            { "num": 163 },
            { "num": 491 },
            { "num": 549 },
            { "num": 319 },
            { "num": 512 },
            { "num": 157 },
            { "num": 486 },
            { "num": 0 }
          ],
          "total": 387.0
        }
      ]
    },
    {
      "title": "Room Type Availability",
      "subData": [
        {
          "title": "Classic",
          "data": [
            { "num": 19 },
            { "num": 90 },
            { "num": 73 },
            { "num": -1 },
            { "num": 11 },
            { "num": 38 },
            { "num": 81 },
            { "num": -2 },
            { "num": 15 },
            { "num": 19 },
            { "num": 92 },
            { "num": 90 },
            { "num": 62 },
            { "num": 13 },
            { "num": 99 },
            { "num": 48 },
            { "num": 73 },
            { "num": 95 },
            { "num": 96 },
            { "num": 70 },
            { "num": 38 },
            { "num": 63 },
            { "num": 38 },
            { "num": 80 },
            { "num": 73 },
            { "num": 70 },
            { "num": 21 },
            { "num": 59 },
            { "num": 37 },
            { "num": 92 },
            { "num": 0 }
          ],
          "total": ""
        },
        {
          "title": "Executive",
          "data": [
            { "num": 15 },
            { "num": 44 },
            { "num": 12 },
            { "num": 41 },
            { "num": 38 },
            { "num": 7 },
            { "num": 6 },
            { "num": -1 },
            { "num": 26 },
            { "num": 40 },
            { "num": 30 },
            { "num": 50 },
            { "num": 37 },
            { "num": 13 },
            { "num": 50 },
            { "num": 28 },
            { "num": 50 },
            { "num": 7 },
            { "num": 27 },
            { "num": 45 },
            { "num": -20 },
            { "num": 41 },
            { "num": 46 },
            { "num": 30 },
            { "num": 29 },
            { "num": 36 },
            { "num": 24 },
            { "num": 26 },
            { "num": 34 },
            { "num": 20 },
            { "num": 0 }
          ],
          "total": ""
        },
        {
          "title": "Delux",
          "data": [
            { "num": 138 },
            { "num": 74 },
            { "num": 23 },
            { "num": 133 },
            { "num": 34 },
            { "num": 85 },
            { "num": 65 },
            { "num": 148 },
            { "num": 102 },
            { "num": 91 },
            { "num": 23 },
            { "num": 73 },
            { "num": 113 },
            { "num": 44 },
            { "num": 111 },
            { "num": 31 },
            { "num": 70 },
            { "num": -5 },
            { "num": 42 },
            { "num": 50 },
            { "num": 11 },
            { "num": 15 },
            { "num": 112 },
            { "num": 8 },
            { "num": -66 },
            { "num": 66 },
            { "num": 124 },
            { "num": 59 },
            { "num": 133 },
            { "num": 34 },
            { "num": 0 }
          ],
          "total": ""
        },
        {
          "title": "Junior Suite",
          "data": [
            { "num": 6 },
            { "num": 10 },
            { "num": 5 },
            { "num": 6 },
            { "num": 5 },
            { "num": 9 },
            { "num": 7 },
            { "num": 7 },
            { "num": 7 },
            { "num": -1 },
            { "num": 8 },
            { "num": 5 },
            { "num": 7 },
            { "num": 8 },
            { "num": 9 },
            { "num": 8 },
            { "num": 5 },
            { "num": 8 },
            { "num": 7 },
            { "num": 9 },
            { "num": 5 },
            { "num": 8 },
            { "num": 9 },
            { "num": 6 },
            { "num": 6 },
            { "num": 8 },
            { "num": 10 },
            { "num": 6 },
            { "num": 5 },
            { "num": 5 },
            { "num": 0 }
          ],
          "total": ""
        },
        {
          "title": "Suite",
          "data": [
            { "num": 5 },
            { "num": 6 },
            { "num": 5 },
            { "num": 8 },
            { "num": 9 },
            { "num": 5 },
            { "num": -1 },
            { "num": 6 },
            { "num": 7 },
            { "num": 6 },
            { "num": 5 },
            { "num": 9 },
            { "num": 8 },
            { "num": 5 },
            { "num": 5 },
            { "num": 7 },
            { "num": 4 },
            { "num": 8 },
            { "num": 6 },
            { "num": 8 },
            { "num": 7 },
            { "num": 6 },
            { "num": 4 },
            { "num": 5 },
            { "num": 6 },
            { "num": 9 },
            { "num": 6 },
            { "num": 7 },
            { "num": 7 },
            { "num": 7 },
            { "num": 0 }
          ],
          "total": ""
        }
      ]
    }
  ]
}
