{
    "data": [
        {
          "name": "0BRM",
          "OCC TY": 206,
          "OCC LY": 102,
          "ADRTY": 247,
          "ADRLY": 426

        },
        {
          "name": "1BRM",
          "OCC TY": 140,
          "OCC LY": 293,
          "ADRTY": 424,
          "ADRLY": 229

        },
        {
          "name": "2BRM",
          "OCC TY": 97,
          "OCC LY": 254,
          "ADRTY": 327,
          "ADRLY": 182
        },
        {
          "name": "3BRM",
          "OCC TY": 114,
          "OCC LY": 84,
          "ADRTY": 259,
          "ADRLY": 410
        },
        {
          "name": "4BRM",
          "OCC TY": 204,
          "OCC LY": 142,
          "ADRTY": 318,
          "ADRLY": 358
        }
      ]
}
